__init__.py
constants/__init__.py
constants/reddit.py
database/__init__.py
database/base_repository.py
database/sqlalchemy/__init__.py
database/sqlalchemy/models.py
database/sqlalchemy/sqlalchemy_repository.py
fs_access/__init__.py
fs_access/base_fs_access.py
fs_access/fs_access_factory.py
fs_access/json_fs_access/__init__.py
fs_access/json_fs_access/json_fs_access.py
travelwise_common-0.17.0.dist-info/METADATA
travelwise_common-0.17.0.dist-info/WHEEL
travelwise_common-0.17.0.dist-info/RECORD
