Metadata-Version: 2.3
Name: travelwise-common
Version: 0.17.0
Summary: 
Author: Gerald Neo
Author-email: gerald.ner56@gmail.com
Requires-Python: >=3.12
Classifier: Programming Language :: Python :: 3
Classifier: Programming Language :: Python :: 3.12
Classifier: Programming Language :: Python :: 3.13
Requires-Dist: black (>=25.1.0,<26.0.0)
Requires-Dist: coverage (>=7.6.12,<8.0.0)
Requires-Dist: pytest (>=8.3.4,<9.0.0)
Requires-Dist: pytest-cov (>=6.0.0,<7.0.0)
Requires-Dist: ruff (>=0.9.7,<0.10.0)
Requires-Dist: sqlalchemy (>=2.0.38,<3.0.0)
